dafact/__init__.py
dafact/__main__.py
dafact/_main.py
dafact/encoders/__init__.py
dafact/encoders/_encoders.py
dafact-0.5.dist-info/LICENSE
dafact-0.5.dist-info/METADATA
dafact-0.5.dist-info/WHEEL
dafact-0.5.dist-info/entry_points.txt
dafact-0.5.dist-info/top_level.txt
dafact-0.5.dist-info/RECORD
