Metadata-Version: 2.1
Name: dafact
Version: 0.5
Summary: Encodes data as ASP facts.
Home-page: https://github.com/bramucas/dafact
Author: Brais Muñiz
Author-email: mc.brais@gmail.com
License: UNKNOWN
Keywords: logic programming,answer set programming
Platform: UNKNOWN
Classifier: Programming Language :: Python :: 3
Classifier: License :: OSI Approved :: MIT License
Classifier: Operating System :: OS Independent
Requires-Python: >=3.6.0
License-File: LICENSE
Requires-Dist: clingo >=5.5.0.post3
Requires-Dist: numpy
Requires-Dist: argparse
